README.rst
setup.py
antfs/__init__.py
antfs.egg-info/PKG-INFO
antfs.egg-info/SOURCES.txt
antfs.egg-info/dependency_links.txt
antfs.egg-info/top_level.txt
tests/__init__.py