Metadata-Version: 1.1
Name: antfs
Version: 1.0.2
Summary: Python3 Apache Ant path patterns matching library
Home-page: https://github.com/Softmotions/antfs
Author: Anton Adamansky
Author-email: adamansky@gmail.com
License: MIT
Keywords: ant,pattern,matching,glob,regexp,file,selector
Platform: UNKNOWN
Classifier: Development Status :: 4 - Beta
Classifier: Intended Audience :: Developers
Classifier: License :: OSI Approved :: MIT License
Classifier: Operating System :: OS Independent
Classifier: Programming Language :: Python :: 3.3
Classifier: Programming Language :: Python :: 3
Classifier: Topic :: Software Development :: Libraries
Classifier: Topic :: Utilities
